[
{
"SchemaVersion":"15.0.0.0","LibraryVersion":"16.0.4756.1000","ErrorInfo":null,"TraceCorrelationId":"d48c399f-af76-70ba-5598-0088764e9d53"
},26,{
"IsNull":false
},27,{
"_ObjectIdentity_":"d48c399f-af76-70ba-5598-0088764e9d53|740c6a0b-85e2-48a0-a494-e0f1759d4aa7:site:fc076364-e921-406c-91fd-36ac4d776bd9:web:94afbc78-a3b9-41b2-bd08-4f09b08ba893"
},29,{
"IsNull":false
},31,{
"IsNull":false
},32,{
"_ObjectType_":"SP.ListItemCollection","_Child_Items_":[
{
"_ObjectType_":"SP.ListItem","_ObjectIdentity_":"d48c399f-af76-70ba-5598-0088764e9d53|740c6a0b-85e2-48a0-a494-e0f1759d4aa7:site:fc076364-e921-406c-91fd-36ac4d776bd9:web:94afbc78-a3b9-41b2-bd08-4f09b08ba893:list:af616b7f-8428-4fbc-99c3-7bb2f051e627:item:6,1","_ObjectVersion_":"4","Title":"kknio","FirstName":"Khouzama","LastName":"Knio","Department":"Biology","JobTitle":"Professor","Email":"kknio@aub.edu.lb","OfficeAddress":"Biology Bldg, 215","Extension":"3886","FullTimer":true,"PublishingPageImage":"<img alt=\"\" src=\"\u002ffas\u002fbiology\u002fPublishingImages\u002fkhouzama%20knio%20140x%20140.jpg\" style=\"BORDER: 0px solid; \">","ProfileDetailsUrl":"\u002fpages\u002fprofile.aspx?MemberId=kknio","Id":6
},{
"_ObjectType_":"SP.ListItem","_ObjectIdentity_":"d48c399f-af76-70ba-5598-0088764e9d53|740c6a0b-85e2-48a0-a494-e0f1759d4aa7:site:fc076364-e921-406c-91fd-36ac4d776bd9:web:94afbc78-a3b9-41b2-bd08-4f09b08ba893:list:af616b7f-8428-4fbc-99c3-7bb2f051e627:item:7,1","_ObjectVersion_":"1","Title":"rtalhouk","FirstName":"Rabih","LastName":"Talhouk","Department":"Biology","JobTitle":"Professor","Email":"rtalhouk@aub.edu.lb","OfficeAddress":"Biology Bldg, 119","Extension":"3895","FullTimer":true,"PublishingPageImage":"<img alt=\"\" src=\"\u002ffas\u002fbiology\u002fPublishingImages\u002frabih%20talhouk%20140x%20140.jpg\" style=\"BORDER: 0px solid; \">","ProfileDetailsUrl":"\u002fpages\u002fprofile.aspx?MemberId=rtalhouk","Id":7
},{
"_ObjectType_":"SP.ListItem","_ObjectIdentity_":"d48c399f-af76-70ba-5598-0088764e9d53|740c6a0b-85e2-48a0-a494-e0f1759d4aa7:site:fc076364-e921-406c-91fd-36ac4d776bd9:web:94afbc78-a3b9-41b2-bd08-4f09b08ba893:list:af616b7f-8428-4fbc-99c3-7bb2f051e627:item:8,1","_ObjectVersion_":"1","Title":"eliasbay","FirstName":"Elias","LastName":"Baydoun","Department":"Biology","JobTitle":"Professor","Email":"eliasbay@aub.edu.lb","OfficeAddress":"Biology Bldg, 319","Extension":"3910","FullTimer":true,"PublishingPageImage":"<img alt=\"\" src=\"\u002ffas\u002fbiology\u002fPublishingImages\u002felias%20baydoun%20140x140.jpg\" style=\"BORDER: 0px solid; \">","ProfileDetailsUrl":"\u002fpages\u002fprofile.aspx?MemberId=eliasbay","Id":8
},{
"_ObjectType_":"SP.ListItem","_ObjectIdentity_":"d48c399f-af76-70ba-5598-0088764e9d53|740c6a0b-85e2-48a0-a494-e0f1759d4aa7:site:fc076364-e921-406c-91fd-36ac4d776bd9:web:94afbc78-a3b9-41b2-bd08-4f09b08ba893:list:af616b7f-8428-4fbc-99c3-7bb2f051e627:item:9,1","_ObjectVersion_":"2","Title":"is08","FirstName":"Imad","LastName":"Saoud","Department":"Biology","JobTitle":"Professor (Chairperson)","Email":"is08@aub.edu.lb","OfficeAddress":"Biology Bldg, 315","Extension":"3913","FullTimer":true,"PublishingPageImage":"<img alt=\"\" src=\"\u002ffas\u002fbiology\u002fPublishingImages\u002fimad%20saoud%20140x140.jpg\" style=\"BORDER: 0px solid; \">","ProfileDetailsUrl":"https:\u002f\u002fsites.aub.edu.lb\u002fis08\u002f","Id":9
},{
"_ObjectType_":"SP.ListItem","_ObjectIdentity_":"d48c399f-af76-70ba-5598-0088764e9d53|740c6a0b-85e2-48a0-a494-e0f1759d4aa7:site:fc076364-e921-406c-91fd-36ac4d776bd9:web:94afbc78-a3b9-41b2-bd08-4f09b08ba893:list:af616b7f-8428-4fbc-99c3-7bb2f051e627:item:10,1","_ObjectVersion_":"1","Title":"cs10","FirstName":"Colin Andrew","LastName":"Smith","Department":"Biology","JobTitle":"Professor","Email":"cs10@aub.edu.lb","OfficeAddress":"Biology Bldg, 313","Extension":"3887","FullTimer":true,"PublishingPageImage":"<img alt=\"\" src=\"\u002ffas\u002fbiology\u002fPublishingImages\u002fcs10.jpg\" style=\"BORDER: 0px solid; \">","ProfileDetailsUrl":"https:\u002f\u002fsites.aub.edu.lb\u002fcs10\u002f","Id":10
},{
"_ObjectType_":"SP.ListItem","_ObjectIdentity_":"d48c399f-af76-70ba-5598-0088764e9d53|740c6a0b-85e2-48a0-a494-e0f1759d4aa7:site:fc076364-e921-406c-91fd-36ac4d776bd9:web:94afbc78-a3b9-41b2-bd08-4f09b08ba893:list:af616b7f-8428-4fbc-99c3-7bb2f051e627:item:11,1","_ObjectVersion_":"2","Title":"sawkreyd","FirstName":"Sawsan","LastName":"Kuraydiyyah","Department":"Biology","JobTitle":"Professor","Email":"sawkreyd@aub.edu.lb","OfficeAddress":"Biology Bldg, 305","Extension":"3906","FullTimer":true,"PublishingPageImage":"<img alt=\"\" src=\"\u002ffas\u002fbiology\u002fPublishingImages\u002fsawsan%20kureydiye%20140x140.jpg\" style=\"BORDER: 0px solid; \">","ProfileDetailsUrl":"\u002fpages\u002fprofile.aspx?MemberId=sawkreyd","Id":11
},{
"_ObjectType_":"SP.ListItem","_ObjectIdentity_":"d48c399f-af76-70ba-5598-0088764e9d53|740c6a0b-85e2-48a0-a494-e0f1759d4aa7:site:fc076364-e921-406c-91fd-36ac4d776bd9:web:94afbc78-a3b9-41b2-bd08-4f09b08ba893:list:af616b7f-8428-4fbc-99c3-7bb2f051e627:item:12,1","_ObjectVersion_":"2","Title":"amro","FirstName":"Hala","LastName":"Muhtasib","Department":"Biology","JobTitle":"Professor","Email":"amro@aub.edu.lb","OfficeAddress":"Biology Bldg, 207","Extension":"3894","FullTimer":true,"PublishingPageImage":"<img alt=\"\" src=\"\u002ffas\u002fbiology\u002fPublishingImages\u002fhala%20muhtasib%20140x140.jpg\" style=\"BORDER: 0px solid; \">","ProfileDetailsUrl":"\u002fpages\u002fprofile.aspx?MemberId=amro","Id":12
},{
"_ObjectType_":"SP.ListItem","_ObjectIdentity_":"d48c399f-af76-70ba-5598-0088764e9d53|740c6a0b-85e2-48a0-a494-e0f1759d4aa7:site:fc076364-e921-406c-91fd-36ac4d776bd9:web:94afbc78-a3b9-41b2-bd08-4f09b08ba893:list:af616b7f-8428-4fbc-99c3-7bb2f051e627:item:13,1","_ObjectVersion_":"1","Title":"mb39","FirstName":"Michel","LastName":"Bariche","Department":"Biology","JobTitle":"Professor","Email":"mb39@aub.edu.lb","OfficeAddress":"Biology Bldg, 105","Extension":"3900","FullTimer":true,"PublishingPageImage":"<img alt=\"\" src=\"\u002ffas\u002fbiology\u002fPublishingImages\u002fmichel%20bariche%20140x140.jpg\" style=\"BORDER: 0px solid; \">","ProfileDetailsUrl":"\u002fpages\u002fprofile.aspx?MemberId=mb39","Id":13
},{
"_ObjectType_":"SP.ListItem","_ObjectIdentity_":"d48c399f-af76-70ba-5598-0088764e9d53|740c6a0b-85e2-48a0-a494-e0f1759d4aa7:site:fc076364-e921-406c-91fd-36ac4d776bd9:web:94afbc78-a3b9-41b2-bd08-4f09b08ba893:list:af616b7f-8428-4fbc-99c3-7bb2f051e627:item:14,1","_ObjectVersion_":"1","Title":"mo07","FirstName":"Mike","LastName":"Osta","Department":"Biology","JobTitle":"Associate Professor","Email":"mo07@aub.edu.lb","OfficeAddress":"Biology Bldg, 209","Extension":"3909","FullTimer":true,"PublishingPageImage":null,"ProfileDetailsUrl":"\u002fpages\u002fprofile.aspx?MemberId=mo07","Id":14
},{
"_ObjectType_":"SP.ListItem","_ObjectIdentity_":"d48c399f-af76-70ba-5598-0088764e9d53|740c6a0b-85e2-48a0-a494-e0f1759d4aa7:site:fc076364-e921-406c-91fd-36ac4d776bd9:web:94afbc78-a3b9-41b2-bd08-4f09b08ba893:list:af616b7f-8428-4fbc-99c3-7bb2f051e627:item:15,1","_ObjectVersion_":"1","Title":"ng13","FirstName":"Noel","LastName":"Ghanem","Department":"Biology","JobTitle":"Associate Professor","Email":"ng13@aub.edu.lb","OfficeAddress":"Biology Bldg, 301","Extension":"3915","FullTimer":true,"PublishingPageImage":"<img alt=\"\" src=\"\u002ffas\u002fbiology\u002fPublishingImages\u002fnoel%20ghanem%20140x140%20.bmp\" style=\"BORDER: 0px solid; \">","ProfileDetailsUrl":"\u002fpages\u002fprofile.aspx?MemberId=ng13","Id":15
},{
"_ObjectType_":"SP.ListItem","_ObjectIdentity_":"d48c399f-af76-70ba-5598-0088764e9d53|740c6a0b-85e2-48a0-a494-e0f1759d4aa7:site:fc076364-e921-406c-91fd-36ac4d776bd9:web:94afbc78-a3b9-41b2-bd08-4f09b08ba893:list:af616b7f-8428-4fbc-99c3-7bb2f051e627:item:16,1","_ObjectVersion_":"1","Title":"dj11","FirstName":"Diana","LastName":"Jaalouk","Department":"Biology","JobTitle":"Associate Professor","Email":"dj11@aub.edu.lb","OfficeAddress":"Biology Bldg, 201","Extension":"3878","FullTimer":true,"PublishingPageImage":"<img alt=\"\" src=\"\u002ffas\u002fbiology\u002fPublishingImages\u002fdiana%20jaalouk%20140x140.jpg\" style=\"BORDER: 0px solid; \">","ProfileDetailsUrl":"\u002fpages\u002fprofile.aspx?MemberId=dj11","Id":16
},{
"_ObjectType_":"SP.ListItem","_ObjectIdentity_":"d48c399f-af76-70ba-5598-0088764e9d53|740c6a0b-85e2-48a0-a494-e0f1759d4aa7:site:fc076364-e921-406c-91fd-36ac4d776bd9:web:94afbc78-a3b9-41b2-bd08-4f09b08ba893:list:af616b7f-8428-4fbc-99c3-7bb2f051e627:item:17,1","_ObjectVersion_":"1","Title":"hb54","FirstName":"Heinrich","LastName":"zu Dohna","Department":"Biology","JobTitle":"Assistant Professor","Email":"hb54@aub.edu.lb","OfficeAddress":"Biology Bldg, 103","Extension":"3905","FullTimer":true,"PublishingPageImage":null,"ProfileDetailsUrl":"\u002fpages\u002fprofile.aspx?MemberId=hb54","Id":17
},{
"_ObjectType_":"SP.ListItem","_ObjectIdentity_":"d48c399f-af76-70ba-5598-0088764e9d53|740c6a0b-85e2-48a0-a494-e0f1759d4aa7:site:fc076364-e921-406c-91fd-36ac4d776bd9:web:94afbc78-a3b9-41b2-bd08-4f09b08ba893:list:af616b7f-8428-4fbc-99c3-7bb2f051e627:item:18,1","_ObjectVersion_":"1","Title":"zk28","FirstName":"Zakaria","LastName":"Kambris","Department":"Biology","JobTitle":"Associate Professor","Email":"zk28@aub.edu.lb","OfficeAddress":"Biology Bldg, 308","Extension":"3911","FullTimer":true,"PublishingPageImage":null,"ProfileDetailsUrl":"\u002fpages\u002fprofile.aspx?MemberId=zk28","Id":18
},{
"_ObjectType_":"SP.ListItem","_ObjectIdentity_":"d48c399f-af76-70ba-5598-0088764e9d53|740c6a0b-85e2-48a0-a494-e0f1759d4aa7:site:fc076364-e921-406c-91fd-36ac4d776bd9:web:94afbc78-a3b9-41b2-bd08-4f09b08ba893:list:af616b7f-8428-4fbc-99c3-7bb2f051e627:item:19,1","_ObjectVersion_":"1","Title":"ns02","FirstName":"Nada","LastName":"Sinnu","Department":"Biology","JobTitle":"Lecturer","Email":"ns02@aub.edu.lb","OfficeAddress":"Biology Bldg, 205","Extension":"3901","FullTimer":true,"PublishingPageImage":"<img alt=\"\" src=\"\u002ffas\u002fbiology\u002fPublishingImages\u002fnada%20sinno%20140x140.png\" style=\"BORDER: 0px solid; \">","ProfileDetailsUrl":"\u002fpages\u002fprofile.aspx?MemberId=ns02","Id":19
},{
"_ObjectType_":"SP.ListItem","_ObjectIdentity_":"d48c399f-af76-70ba-5598-0088764e9d53|740c6a0b-85e2-48a0-a494-e0f1759d4aa7:site:fc076364-e921-406c-91fd-36ac4d776bd9:web:94afbc78-a3b9-41b2-bd08-4f09b08ba893:list:af616b7f-8428-4fbc-99c3-7bb2f051e627:item:20,1","_ObjectVersion_":"1","Title":"rsadek","FirstName":"Riyad","LastName":"Sadek","Department":"Biology","JobTitle":"Lecturer","Email":"rsadek@aub.edu.lb","OfficeAddress":"Biology Bldg, 101","Extension":"3890","FullTimer":true,"PublishingPageImage":"<img alt=\"\" src=\"\u002ffas\u002fbiology\u002fPublishingImages\u002friyad%20sadek%20140x140.jpg\" style=\"BORDER: 0px solid; \">","ProfileDetailsUrl":"\u002fpages\u002fprofile.aspx?MemberId=rsadek","Id":20
},{
"_ObjectType_":"SP.ListItem","_ObjectIdentity_":"d48c399f-af76-70ba-5598-0088764e9d53|740c6a0b-85e2-48a0-a494-e0f1759d4aa7:site:fc076364-e921-406c-91fd-36ac4d776bd9:web:94afbc78-a3b9-41b2-bd08-4f09b08ba893:list:af616b7f-8428-4fbc-99c3-7bb2f051e627:item:21,1","_ObjectVersion_":"1","Title":"hr00","FirstName":"Hind","LastName":"Rizkallah","Department":"Biology","JobTitle":"Lecturer","Email":"hr00@aub.edu.lb","OfficeAddress":"Biology Bldg, 106A","Extension":"3897","FullTimer":true,"PublishingPageImage":null,"ProfileDetailsUrl":"\u002fpages\u002fprofile.aspx?MemberId=hr00","Id":21
},{
"_ObjectType_":"SP.ListItem","_ObjectIdentity_":"d48c399f-af76-70ba-5598-0088764e9d53|740c6a0b-85e2-48a0-a494-e0f1759d4aa7:site:fc076364-e921-406c-91fd-36ac4d776bd9:web:94afbc78-a3b9-41b2-bd08-4f09b08ba893:list:af616b7f-8428-4fbc-99c3-7bb2f051e627:item:22,1","_ObjectVersion_":"1","Title":"lh00","FirstName":"Layane","LastName":"Hajjar","Department":"Biology","JobTitle":"Instructor","Email":"lh00@aub.edu.lb","OfficeAddress":"Biology Bldg, 106A","Extension":"3920","FullTimer":true,"PublishingPageImage":null,"ProfileDetailsUrl":"\u002fpages\u002fprofile.aspx?MemberId=lh00","Id":22
},{
"_ObjectType_":"SP.ListItem","_ObjectIdentity_":"d48c399f-af76-70ba-5598-0088764e9d53|740c6a0b-85e2-48a0-a494-e0f1759d4aa7:site:fc076364-e921-406c-91fd-36ac4d776bd9:web:94afbc78-a3b9-41b2-bd08-4f09b08ba893:list:af616b7f-8428-4fbc-99c3-7bb2f051e627:item:23,1","_ObjectVersion_":"1","Title":"ma73","FirstName":"Mohammad","LastName":"Al-Zein","Department":"Biology","JobTitle":"Instructor","Email":"ma73@aub.edu.lb","OfficeAddress":"Biology Bldg, 101A","Extension":"3896","FullTimer":true,"PublishingPageImage":"<img alt=\"\" src=\"\u002ffas\u002fbiology\u002fPublishingImages\u002fmohamad%20elzein%20140x140.jpg\" style=\"BORDER: 0px solid; \">","ProfileDetailsUrl":"\u002fpages\u002fprofile.aspx?MemberId=ma73","Id":23
}
]
}
]